Metadata-Version: 1.1
Name: EZMathPY
Version: 1.0.0
Summary: a simple python math calculator
Home-page: UNKNOWN
Author: strikerz
Author-email: jysonok@gmail.com
License: MIT
Keywords: calculator,math,easy,statistics
Platform: UNKNOWN
Classifier: Development Status :: 5 - Production/Stable
Classifier: Intended Audience :: Education
Classifier: Operating System :: Microsoft :: Windows :: Windows 10
Classifier: License :: OSI Approved :: MIT License
Classifier: Programming Language :: Python :: 3
